{"songs": [{"title": "Long Stretch of Love", "album": "747 ", "year": "2014-09-30", "lyrics": "[Verse 1]\nYou're hit then miss, you're fire and ice\nYou're water and whiskey burn\nWe kiss, we fight, make up all night\nYou're the blessing and the curse\n\nBut I don\u2019t ever wanna break this chain\nI don\u2019t ever wanna walk away\nCause I ain't ever gonna find another lover\nWho\u2019ll make me feel this way\n\n[Pre-Chorus]\nOver and over and over, we say that we're through\nBut I come right back to you\n\n[Chorus]\nThere's a long stretch of love coming down the line\nI'm your rock that won\u2019t ever roll and baby, you\u2019ll be mine\nI'll be right here beside you when these good times get tough\nBaby, we're in for a long stretch of love\n\n[Verse 2]\nYou lift me up, you bring me down\nYou make me feel alive\nYou send my heart in overdrive\nEvery time you kill the lights\n\n[Pre-Chorus]\nOver and over and over, we play this game\nWin or lose, we'll never change\n\n[Chorus]\nThere's a long stretch of love coming down the line\nI'm your rock that won\u2019t ever roll and baby, you\u2019ll be mine\nI'll be right here beside you when these good times get tough\nBaby, we're in for a long stretch of love\n\n[Bridge]\nLong stretch of love, long stretch of love, long stretch of love\nOver and over and over, we play this game\nWin or lose, we'll never change\n\n[Chorus]\nThere's a long stretch of love coming down the line\nI'm your rock that won\u2019t ever roll and baby, you\u2019ll be mine\nI'll be right here beside you when these good times get tough\nBaby, we're in for a long stretch of love\n\nLong stretch of love\nLong stretch of love\nLong stretch of love\n\n[Outro]\nI don\u2019t wanna break this chain\nI ain't gonna walk away in this long stretch of love", "image": "https://images.genius.com/bc052f6cd503980c60ace817ccc0ce3c.1000x1000x1.jpg"}], "artist": "Lady Antebellum"}