{"songs": [{"title": "On My Highway", "album": "Wide Open", "year": "2009-04-07", "lyrics": "[Verse 1]\nOn my highway the yellow lines\nHave disappeared from time to time\nAnd I've wound up on the wrong side of the road\nOn my highway I've gone too fast\nAfraid that I might finish last\nI hugged the curve too hard and lost control\nOh I never know which way it's going to go\n\n[Chorus]\nBut what a feeling, chasing the sun\nLiving my life like it's shot from a gun\nLaughing a little bit more with every mile\nOh what a freedom racing the wind\nDying to know what's around the next bend\nAnd smiling as I watch the years roll by\nI'm learning how to take it day by day on my highway\n\n[Verse 2]\nOn my highway I missed some signs\nAnd left a damn good love behind\nI see her in my rearview like a ghost\nOn my highway I've broken down\nAnd cried when no one else was around\nAnd prayed that God would take my soul\nYeah I've paid a lot of heavy tolls\n\n[Chorus]\nBut what a feeling, chasing the sun\nLiving my life like it's shot from a gun\nLaughing a little bit more with every mile\nOh what a freedom racing the wind\nDying to know what's around the next bend\nAnd smiling as I watch the years roll by\nI'm learning how to take it day by day on my highway\n\nYeah, yeah\nWhat a feeling out on the run\nDrinking up the rain, soaking up the sun\nLaughing a little bit more with every mile\nOh what a freedom, like a sail in the wind\nNot looking back, not forgetting where I've been\nSmiling as I watch the years roll by\nAnd I'm moving on from my mistakes\nAnd I'm learning how to take it day by day on my highway\n\n[Outro]\nOh oh, yeah", "image": "https://images.genius.com/8da66aa72669c7ca33ae335e1fed1642.1000x1000x1.jpg"}], "artist": "Jason Aldean"}