{"songs": [{"title": "You and the Beach", "album": "Spring Break... Checkin\u2019 Out", "year": null, "lyrics": "[Verse 1]\nMy shoulder still burns\nMy head still hurts\nThere's sand from your shoes in my floorboard\nLipstick on my straw, you're crying out\nI paint it in my rear view\nMy speaker still blasts that song\nThat you turn me on to\n\n[Chorus]\nIt's like that blue water ran up the highway\nThe salt air is pulling on my tailgate\nAnd that sunset is still hanging on\nI left the lights, the cars, the parties on the strip\nThe up all nights and your sunrise kiss\nYeah I was a fool to think I could just move on\nCause you and the beach follow me home\n\n[Verse 2]\nStill hear your words saying we can't do this\nCause you're up there and I'm down here\nBaby let's go on and face it\n\n[Chorus]\nIt's like that blue water ran up the highway\nIt's so intense, it's blowing out my tail gate\nAnd that sunset is still hanging on\nI left the lights, the cars, the parties on the strip\nThe up all nights and your sunrise kiss\nYeah I was a fool to think I could just move on\nCause you and the beach follow me home\nI left the lights, the cars, the parties on the strip\nThe up all nights and your sunrise kiss\nYeah I was a fool to think I could just move on\n\u00b4Cause there you are everytime I close my eyes\nIs like we never even say good bye\nIt don\u00b4t feel like you are really gone\nYou and the beach follow me home", "image": "https://images.genius.com/0b62dc359f6da185fdd17b488038864c.1000x1000x1.jpg"}], "artist": "Luke Bryan"}