{"songs": [{"title": "Sunburnt Lips", "album": "Crash My Party", "year": "2013-08-13", "lyrics": "[Verse 1]\nBack again in the back of this pasture\nSweatin' bad in the cab of this tractor\nI oughta be worried about the rain\nThe last hundred rows could've been a little straighter\nGuess I'll be hittin' them again later\nI could turn this red dirt all day, yeah\n\n[Chorus]\nDreamin' 'bout sunburnt lips on me, all summer long\nWe were tangled up in a blanket on the sand\nAnd the moonlight, watchin' that tide roll in\nHer skin on mine, the only thing I got on my mind\nIs a two-piece memory of her and me layin' on the beach\nAnd her sunburnt lips on me, yeah, her sunburnt lips\n\n[Verse 2]\nBehind the dust is a big ol' blue sky\nKinda reminds me of those blue eyes smilin' back at me\nI slide up a gear and go a little faster\nJust a little breeze and I'm right back there\nAnd I can almost feel\n\n[Chorus]\nHer sunburnt lips on me, all summer long\nWe were tangled up in a blanket on the sand\nAnd the moonlight, watchin' that tide roll in\nHer skin on mine, the only thing I got on my mind\nIs a two-piece memory of her and me layin' on the beach\nAnd her sunburnt lips on me, yeah, her sunburnt lips\nOh, sunburnt lips, sunburnt lips, sunburnt lips\nSunburnt lips on me, all summer long\nWe were tangled up in a blanket on the sand\nAnd the moonlight, watchin' that tide roll in\nHer skin on mine, the only thing I got on my mind\nIs a two-piece memory of her and me layin' on the beach\nAnd one sweet, sweet memory of layin' on the beach\nWith her sunburnt lips on me, yeah, her sunburnt lips\nSunburnt lips on me, yeah, her sunburnt lips", "image": "https://images.genius.com/87c143421d97cdd9a6027cca31ea51e5.1000x1000x1.jpg"}], "artist": "Luke Bryan"}