{"songs": [{"title": "Take Take Take", "album": "Unreleased Songs", "year": null, "lyrics": "[Verse 1]\nYou give me love\nBut then you take it away\nAnd I'm left to search where to hide\nYou give me love (Love), love (Love)\nAll of your eyes that have cursed me countless times\n\n[Pre-Chorus]\nI think I'm cursed\nI think I'm dying for days\nAs I build to the top with you\nYou give me love (Love), love (Love)\nAll of your eyes that have cursed me countless times, oh\n\n[Chorus]\nTake, take, take\nBut don't give it back now\nWait, wait, wait\nI've loaded up a gun\nBang, bang, bang\nCome in from your back door\nHang, hang, hang\nMe up on your wall\n\n[Verse 2]\nYou give me angst\nOh, all I need is a break\nFrom your clever little lies\nYou give me love (Love), love (Love)\nAll of your eyes that have cursed me countless times\n\n[Pre-Chorus]\nI think I'm cursed\nI think I'm dying for days\nAs I build to the top with you\nYou give me love (Love), love (Love)\nAll of your eyes that have cursed me countless times, oh\n\n[Chorus]\nTake, take, take\nBut don\u2019t give it back now\nWait, wait, wait\nI've loaded up a gun\nBang, bang, bang\nCome in from your back door\nHang, hang, hang\nMe up on your wall\n\n[Bridge]\nIt's 2 AM in the city of sin, it's 2 AM in the city of sin\nAh, ah, ah\nIt's 2 AM in the city of sin, it's 2 AM in the city of sin\nIt's 2 AM in the city of sin, it's 2 AM in the city of sin\nIt's 2 AM in the city of sin, it's 2 AM in the city of sin\n\n[Chorus]\nTake, take, take\nBut don't give it back now\nWait, wait, wait\nI've loaded up a gun\nBang, bang, bang\nCome in from your back door\nHang, hang, hang\nMe up on your wall", "image": "https://images.genius.com/6abeb1423d1300847b67b86f6d6df07f.1000x1000x1.jpg"}], "artist": "Imagine Dragons"}