{"songs": [{"title": "Hangin\u2019 Around", "album": "Desperate Man", "year": "2018-10-05", "lyrics": "[Verse 1]\nHow you spin, hit the door, and get myself on down the road\nI picked my clothes up off the floor and on the wind I go\nLet it blow me where the wild is, thought I was off better\nHolding on to nothing, but they're holding me together\n\n[Chorus]\nLook at me hangin' around\nHangin' around\nHangin' around (Ooh)\nHangin' around (Ooh)\n\n[Post-Chorus]\nMake me sweat, sweat\nBreaking out a fever, I get cranky\nSo hot, hot\nDamn hot, shakes it, I get shake, shake\n\n[Verse 3]\nI rock to my own rhythm (I rock)\nI roll to my own beat (I, I, I roll)\nI play the movie villain\nNow you got me playing for keeps\n\n[Chorus]\nHangin' around (Ooh)\nHangin' around\nHangin' around (Ooh)\nHangin' around (Ooh)\n(Help me)\n\n[Post-Chorus]\nMake me sweat, sweat\nBreaking out a fever, I get cranky\nGet so hot, hot\nDamn hot, shake it like you shake, shake\n\n[Verse 5]\nStrangest change of places (I rock)\nWe're just scared today (I, I, I roll)\nShe's the one holding my aces\nAnd I'm the one holding my breath\n\n[Chorus]\nHangin' around (Ooh, yeah)\nHangin' around (Ooh)\nHangin' around (Ooh, ooh)\nHangin' around (Ooh)\nAh, ah, ah, ah, ah, ah (Ooh)\n(Ooh)", "image": "https://images.genius.com/54c8206050910c36c256b33cdd3da339.630x630x1.jpg"}], "artist": "Eric Church"}