{"songs": [{"title": "The Fall", "album": "Smoke + Mirrors", "year": "2015-02-17", "lyrics": "[Instrumental Intro]\n\n[Verse 1]\nMaybe I'm broken, maybe I'm wrong\nI could've spoken sooner than I should've\nOnly the good die old\nThat's what they told me, but I don't know\n\n[Pre-Chorus]\nMaybe I'm breaking up with myself\nMaybe I'm thinking\nI should just keep to the things that I've been told\nWait for the colors to turn to gold\n\n[Chorus]\nDo you know? Do you know?\nYou're all I know, you're all I know\nEverything comes crashing down\nYou're all I know, you're all I know\n\n[Post-Chorus]\nI'm ready for the fall\nI'm ready for everything\nThat I believed in to drift away\nI'm ready for the leaves\nReady for the colors to burn to gold and crumble away\n\n[Verse 2]\nMaybe I'm destined to be distraught\nAlways a reason, breaking me down to my\nKnees in the dead of night\nI keep on praying to see the light, oh-oh-oh\n\n[Pre-Chorus]\nMaybe I'm breaking up with myself\nMaybe I'm thinking\nI should just keep to the things that I've been told\nWait for the colors to turn to gold\n\n[Chorus]\nDo you know? Do you know?\nYou're all I know, you're all I know\nEverything comes crashing down\nYou're all I know, you're all I know\nDo you know? Do you know?\nYou're all I know, you're all I know\nEverything comes crashing down\nYou're all I know, you're all I know\n\n[Post-Chorus]\nI'm ready for the fall\nI'm ready for everything\nThat I believed in to drift away\nI'm ready for the leaves\nReady for the colors to burn to gold and crumble away\n\n[Interlude]\n\n[Bridge]\nYou were the one, you were the one\nYou were the one who helped me see\nYou were the one, you were the one\nOh, you gave it all to me\nYou were the one, you were the one\nYou were the one who helped me see\nYou were the one, you were the one\nOh, you gave it all to me\nYou were the one, you were the one\nYou were the one who helped me see\nYou were the one, you were the one\nOh, you gave it all to me\nYou were the one, you were the one\nYou were the one who helped me see\nYou were the one, you were the one\nOh, you gave it all to me\nYou were the one, you were the one\nYou were the one who helped me see\nYou were the one, you were the one\nOh, you gave it all to me\n\n[Breakdown]\nYou were the one, you were the one\n(Do you know? Do you know?)\nYou were the one who helped me see\n(You're all I know, you're all I know)\nYou were the one, you were the one\n(Everything comes crashing down)\nOh, you gave it all to me\n(You're all I know, you're all I know)\n\n[Outro]\nI'm ready for the fall\nReady for the leaves\nReady for the colors to burn to gold and crumble away", "image": "https://images.genius.com/043aba598b4c70a34246879f6e419816.1000x1000x1.jpg"}], "artist": "Imagine Dragons"}