{"songs": [{"title": "I\u2019m So Sorry", "album": "Smoke + Mirrors", "year": "2015-02-17", "lyrics": "[Intro]\n\n[Verse 1]\nAbout time for anyone telling you\nOff for all your deeds\nNo sign the roaring thunder\nStopped in cold to read (No time)\n\n[Pre-Chorus]\nI get mine and make no excuses\nWaste of precious breath (no time)\nThe sun shines on everyone\nEveryone, love yourself to death\n\n[Chorus]\nSo you gotta fire up, you gotta let go\nYou'll never be loved 'til you\u2019ve made your own\nYou gotta face up, you gotta get yours\nYou never know the top 'til you get too low\n\n[Post-Chorus]\nA son of a stepfather\nA son of a, I'm so sorry\nA son of a stepfather\nA son of a, I'm so sorry\n\n[Verse 2]\nNo lies and no deceiving\nMan is what he loves\nI keep tryin' to conceive that\nDeath is from above (No time)\n\n[Pre-Chorus]\nI get mine and make no excuses\nWaste of precious breath (No time)\nThe sun shines on everyone\nEveryone, love yourself to death\n\n[Chorus]\nSo you gotta fire up, you gotta let go\nYou'll never be loved 'til you\u2019ve made your own\nYou gotta face up, you gotta get yours\nYou never know the top 'til you get too low\n\n[Post-Chorus]\nA son of a stepfather\nA son of a, I'm so sorry\nA son of a stepfather\nA son of a, I'm so sorry\n\n[Bridge]\nLife isn't always what you think it\u2019d be\nTurn your head for one second and the tables turn\nAnd I know, I know that I did you wrong\nBut will you trust me when I say that I'll make it up to you?\nSomehow, somehow?\n\n[Chorus]\nSo you gotta fire up, you gotta let go\nYou'll never be loved 'til you\u2019ve made your own\nYou gotta face up, you gotta get yours\nYou never know the top 'til you get too low\n\n[Post-Chorus]\nA son of a stepfather\nA son of a, I'm so sorry\nA son of a stepfather\nA son of a, I'm so sorry\nI'm so sorry\nI'm so sorry\nI'm so sorry\nA son of a\n\n[Outro: Guitar Solo]", "image": "https://images.genius.com/3b406b52b4aeebd6e984c9332deb489d.600x600x1.jpg"}], "artist": "Imagine Dragons"}