{"songs": [{"title": "Addicted", "album": "All About Tonight EP", "year": null, "lyrics": "[Verse 1]\nShe says she hates to sleep alone but she'll do it tonight\nShe wants to grab her telephone but she knows it aren\u2019t right\nSo if he won't call, she'll survive\nAnd if he don't care, she'll get by\nClimb into bed, bury her head and cry\n\nFrom the beginning he was all anyone could have been\nThey were delirious with love, they were certain to win\nNow he's breaking plans more and more\nAnd he's leaving notes on her door\nTook a trip out of town, couldn't turn this one down\nHe said I guess I should've told you before\n\n[Chorus]\nShe says she feel like she's addicted to a real bad thing\nAlways sitting, waiting, wondering if the phone will ring\nShe knows she bounces like a yoyo when he pulls her strings\nIt hurts to feel like such a fool\nShe wants to tell him not to call or come around again\nHe doesn't need her now in all the ways that she needs him\nShe's on the edge about to fall from leaning out again\nShe doesn't know which way to move\nOh no\n\n[Verse 2]\nShe wants to be fair, she couldn't say he was ever unkind\nIf she could bear to walk away, she thinks he wouldn't mind\nCause he just keeps himself so apart\nAnd there's no one else in her heart\nSo she's taking a dive from an emotional high and coming down hard\n\n[Chorus]\nShe says she feel like she's addicted to a real bad thing\nAlways sitting, waiting, wondering if the phone will ring\nShe knows she bounces like a yoyo when he pulls her strings\nIt hurts to feel like such a fool\nShe wants to tell him not to call or come around again\nHe doesn't need her now in all the ways that she needs him\nShe's on the edge, about to fall from leaning out again\nShe doesn't know which way to move\nIt hurts to feel like such a fool because she don't know which way to move\nIt hurts to feel like such a fool", "image": "https://images.genius.com/3f2835e12930a3506333b1e5e03b7a33.500x500x1.jpg"}], "artist": "Blake Shelton"}