{"songs": [{"title": "Battle Cry", "album": "Smoke + Mirrors (Deluxe)", "year": "2014-06-02", "lyrics": "[Verse 1]\nJust one more time\nBefore I go, I'll let you know\nThat all this time I've been afraid\nWouldn't let it show\nNobody can save me now, no\nNobody can save me now\n\n[Verse 2]\nStars are only visible in darkness\nFear is ever changing and evolving\nAnd I, I feel poisoned inside\nBut I, I feel so alive\n\n[Chorus]\nNobody can save me now\nKing is crowned\nIt's do or die\nNobody can save me now\nThe only sound\nIs the battle cry\nIs the battle cry\nIs the battle cry\nNobody can save me now\nIt's do or die\n\n[Chorus]\nNobody can save me now\nKing is crowned\nIt's do or die\nNobody can save me now\nThe only sound\nIs the battle cry\nIs the battle cry\nIs the battle cry\nNobody can save me now\nIt's do or die\n\n[Outro]\nJust one more time\nBefore I go, I'll let you know\nThat all this time I've been afraid\nWouldn't let it show\nNobody can save me now, no\nNobody can save me now", "image": "https://images.rapgenius.com/1f5d6179d58403c93eeef45e0e63e121.1000x1000x1.png"}], "artist": "Imagine Dragons"}