{"songs": [{"title": "If My Truck Could Talk", "album": "Old Boots, New Dirt", "year": "2014-10-07", "lyrics": "[Verse 1]\nTwelve gauge, old Ford, buckshot floorboard, don't ask\nFence post, door dent, let's just leave it at that\nIt's got dirt on me, yeah I'd be up a tree\n\n[Chorus]\nIf my truck could talk, I'd have to yank out all the wires\nPour on the gas, set it on fire, anything to shut it up\nIt's been good to me but it knows too much, he'd sing it all\nI'd have to find a riverbank and roll it off\nIf my truck could talk\n\n[Verse 2]\nThose two headlights, looked in her eyes, how she danced\nMoonlit truck bed, two kids, enough said, yeah man\nAll that went on, goes on my own\nIt can go on and on and on\n\n[Chorus]\nIf my truck could talk, I'd have to yank out all the wires\nPour on the gas, set it on fire, anything to shut it up\nIt's been good to me but it knows too much, he'd sing it all\nI'd have to find a riverbank and roll it off\nIf my truck could talk\n\nIf my truck could talk I couldn't deny a word it said\nI'd just smile and shake my head, yeah\nIt's been good to me but it knows too much, he'd sing it all\nI'd have to find a riverbank and roll it off\nIf my truck could talk, if my truck could talk\nIf my truck could talk", "image": "https://images.genius.com/4193b956084d11cca4d63ffd6c3f1725.1000x1000x1.jpg"}], "artist": "Jason Aldean"}